circe_client/__init__.py
circe_client_certic-0.0.8.dist-info/METADATA
circe_client_certic-0.0.8.dist-info/WHEEL
circe_client_certic-0.0.8.dist-info/RECORD
